cm_colors/__init__.py
cm_colors/core/__init__.py
cm_colors/core/cm_colors.py
cm_colors/core/color_metrics.py
cm_colors/core/color_parser.py
cm_colors/core/colors.py
cm_colors/core/contrast.py
cm_colors/core/conversions.py
cm_colors/core/named_colors.py
cm_colors/core/optimisation.py
cm_colors-0.2.1.dist-info/licenses/LICENSE
cm_colors-0.2.1.dist-info/METADATA
cm_colors-0.2.1.dist-info/WHEEL
cm_colors-0.2.1.dist-info/top_level.txt
cm_colors-0.2.1.dist-info/RECORD
