Metadata-Version: 2.4
Name: cm-colors
Version: 0.2.1
Summary: You pick your colors, we make it readable
Home-page: https://github.com/comfort-mode-toolkit/cm-colors
Author: Lalitha A R
Author-email: arlalithablogs@gmail.com
Project-URL: Documentation, https://comfort-mode-toolkit.readthedocs.io/en/latest/cm_colors/installation.html
Project-URL: Bug Reports, https://github.com/comfort-mode-toolkit/cm-colors/issues
Project-URL: Source, https://github.com/comfort-mode-toolkit/cm-colors
Classifier: Programming Language :: Python :: 3
Classifier: License :: OSI Approved :: GNU General Public License v3 (GPLv3)
Classifier: Operating System :: OS Independent
Classifier: Development Status :: 4 - Beta
Classifier: Intended Audience :: Developers
Classifier: Topic :: Software Development :: Libraries :: Python Modules
Classifier: Topic :: Multimedia :: Graphics
Classifier: Topic :: Scientific/Engineering
Requires-Python: >=3.7
License-File: LICENSE
Dynamic: author
Dynamic: author-email
Dynamic: classifier
Dynamic: description
Dynamic: description-content-type
Dynamic: home-page
Dynamic: license-file
Dynamic: project-url
Dynamic: requires-python
Dynamic: summary
